vz_utils/__init__.py
vz_utils/_utils.py
vz_utils/test_dummy.py
vz_utils-0.1.0.dist-info/METADATA
vz_utils-0.1.0.dist-info/WHEEL
vz_utils-0.1.0.dist-info/top_level.txt
vz_utils-0.1.0.dist-info/RECORD
