Metadata-Version: 2.1
Name: vz_utils
Version: 0.1.0
Summary: util functions for visualization
Author: Injae Lee
Author-email: inwo9091@gmail.com
Requires-Dist: matplotlib >=3.8.4
